setup.cfg
setup.py
scripts/fume
src/fume/__init__.py
src/fume/__main__.py
src/fume/expectations.py
src/fume/parse.py
src/fume/results.py
src/fume/script.py
src/fume.egg-info/PKG-INFO
src/fume.egg-info/SOURCES.txt
src/fume.egg-info/dependency_links.txt
src/fume.egg-info/requires.txt
src/fume.egg-info/top_level.txt