Metadata-Version: 1.0
Name: fume
Version: 0.1.2
Summary: Fume: a smoke test scripting language
Home-page: UNKNOWN
Author: Christian Fernandez
Author-email: c@hackbrightacademy.com
License: UNKNOWN
Platform: UNKNOWN
